sphinx_autodoc_toml/__init__.py
sphinx_autodoc_toml/extension.py
sphinx_autodoc_toml/linter.py
sphinx_autodoc_toml/parser.py
sphinx_autodoc_toml-0.1.5.dist-info/WHEEL
sphinx_autodoc_toml-0.1.5.dist-info/entry_points.txt
sphinx_autodoc_toml-0.1.5.dist-info/METADATA
sphinx_autodoc_toml-0.1.5.dist-info/RECORD
