Metadata-Version: 2.3
Name: sphinx-autodoc-toml
Version: 0.1.5
Summary: A Sphinx extension for documenting TOML configuration files with embedded directives
Author: sphinx-autodoc-toml contributors
License: MIT License
Classifier: Development Status :: 3 - Alpha
Classifier: Framework :: Sphinx :: Extension
Classifier: Intended Audience :: Developers
Classifier: License :: OSI Approved :: MIT License
Classifier: Programming Language :: Python :: 3
Classifier: Programming Language :: Python :: 3.8
Classifier: Programming Language :: Python :: 3.9
Classifier: Programming Language :: Python :: 3.10
Classifier: Programming Language :: Python :: 3.11
Classifier: Programming Language :: Python :: 3.12
Classifier: Topic :: Documentation
Classifier: Topic :: Documentation :: Sphinx
Requires-Dist: sphinx>=5.0
Requires-Dist: tomlkit>=0.11.0
Requires-Dist: pytest>=7.0 ; extra == 'dev'
Requires-Dist: pytest-cov>=4.0 ; extra == 'dev'
Requires-Dist: sphinx-needs>=1.0 ; extra == 'dev'
Requires-Dist: types-docutils>=0.20 ; extra == 'dev'
Requires-Python: >=3.8
Project-URL: Homepage, https://github.com/calvingiles/autodoc-toml
Project-URL: Issues, https://github.com/calvingiles/autodoc-toml/issues
Project-URL: Repository, https://github.com/calvingiles/autodoc-toml
Provides-Extra: dev
